Metadata-Version: 2.1
Name: datasette-scraper
Version: 0.5.3
Summary: Adds website scraping abilities to Datasette.
Home-page: https://github.com/cldellow/datasette-scraper
Author: Colin Dellow
License: Apache License, Version 2.0
Project-URL: Issues, https://github.com/cldellow/datasette-scraper/issues
Project-URL: CI, https://github.com/cldellow/datasette-scraper/actions
Project-URL: Changelog, https://github.com/cldellow/datasette-scraper/releases
Classifier: Framework :: Datasette
Classifier: License :: OSI Approved :: Apache Software License
Requires-Python: >=3.7
License-File: LICENSE
License-File: COPYING
Requires-Dist: datasette
Requires-Dist: selectolax
Requires-Dist: datasette-template-sql
Requires-Dist: pluggy
Requires-Dist: httpx
Requires-Dist: zstandard
Requires-Dist: more-itertools
Provides-Extra: test
Requires-Dist: wheel ; extra == 'test'
Requires-Dist: pytest ; extra == 'test'
Requires-Dist: pytest-asyncio ; extra == 'test'
Requires-Dist: pytest-watch ; extra == 'test'
Requires-Dist: coverage ; extra == 'test'
